pype/__init__.py
pype/__main__.py
pype/config-schema.json
pype/config_handler.py
pype/config_model.py
pype/constants.py
pype/core.py
pype/errors.py
pype/template.py
pype/template_minimal.py
pype/type_plugin.py
pype/type_pype.py
pype/config/__init__.py
pype/config/logger.py
pype/config/plugin_register.py
pype/config/plugin_unregister.py
pype/config/shell_install.py
pype/config/shell_uninstall.py
pype/config/system_info.py
pype/util/__init__.py
pype/util/benchmark.py
pype/util/cli.py
pype/util/iotools.py
pype/util/multi_cmd.py
pype_cli-0.8.1.dist-info/LICENSE.txt
pype_cli-0.8.1.dist-info/METADATA
pype_cli-0.8.1.dist-info/README.md
pype_cli-0.8.1.dist-info/WHEEL
pype_cli-0.8.1.dist-info/config-schema.json
pype_cli-0.8.1.dist-info/entry_points.txt
pype_cli-0.8.1.dist-info/top_level.txt
pype_cli-0.8.1.dist-info/RECORD
