Metadata-Version: 2.1
Name: pype-cli
Version: 0.8.1
Summary: A command-line tool for command-line tools
Home-page: https://github.com/BastiTee/pype
Author: Basti Tee
Author-email: basti.tee@icloud.com
License: Apache 2.0
Keywords: development
Classifier: Natural Language :: English
Classifier: Environment :: Console
Classifier: Intended Audience :: Developers
Classifier: License :: OSI Approved :: Apache Software License
Classifier: Programming Language :: Python
Classifier: Programming Language :: Python :: 3.9
Classifier: Programming Language :: Python :: 3.10
Classifier: Programming Language :: Python :: 3.11
Classifier: Programming Language :: Python :: 3.12
Classifier: Programming Language :: Python :: 3.13
Requires-Python: >=3.9
License-File: LICENSE.txt
License-File: README.md
License-File: pype/config-schema.json
Requires-Dist: click
Requires-Dist: jsonschema
Requires-Dist: dacite
Requires-Dist: tabulate
Requires-Dist: colorama
